codefactory/__init__.py
codefactory/codef.py
codefactory/template.py
codefactory/toolchains.py
codefactory/utils.py
codefactory/click/__init__.py
codefactory/click/_bashcomplete.py
codefactory/click/_compat.py
codefactory/click/_termui_impl.py
codefactory/click/_textwrap.py
codefactory/click/_unicodefun.py
codefactory/click/_winconsole.py
codefactory/click/core.py
codefactory/click/decorators.py
codefactory/click/exceptions.py
codefactory/click/formatting.py
codefactory/click/globals.py
codefactory/click/parser.py
codefactory/click/termui.py
codefactory/click/testing.py
codefactory/click/types.py
codefactory/click/utils.py
codefactory-0.7.0.data/data/share/codefactory/templates/cpp.zip
codefactory-0.7.0.data/data/share/codefactory/templates/cpplib.zip
codefactory-0.7.0.dist-info/DESCRIPTION.rst
codefactory-0.7.0.dist-info/METADATA
codefactory-0.7.0.dist-info/RECORD
codefactory-0.7.0.dist-info/WHEEL
codefactory-0.7.0.dist-info/entry_points.txt
codefactory-0.7.0.dist-info/metadata.json
codefactory-0.7.0.dist-info/top_level.txt
codefactory-0.7.0.dist-info/zip-safe
