Metadata-Version: 2.0
Name: codefactory
Version: 0.7.0
Summary: a native code builder using git, github service and cmake
Home-page: https://github.com/sunxfancy/codefactory
Author: sunxfancy
Author-email: sunxfancy@gmail.com
License: MIT
Keywords: codef code factory builder cmake github
Platform: UNKNOWN
